mux.v
module mux(input_1, input_2, switch, result);

    input wire input_1, input_2, switch;
    output wire result;

    wire and_1;
    wire and_2;

    assign and_1 = input_1 && ~switch;
    assign and_2 = input_2 && switch;
    assign result = and_1 || and_2;

endmodule

mux_tb.v
`timescale 1ns / 1ns
`include "mux.v"

module mux_tb;

reg I1, I2, S;
wire R;

mux uut(I1, I2, S, R);

initial begin
    $dumpfile("mux_tb.vcd");
    $dumpvars(0, mux_tb);

    // test first AND gate
    S = 0;

    // 00 => 0
    I2 = 0;
    I1 = 0;
    #20;

    // 01 => 0
    I2 = 0;
    I1 = 1;
    #20;

    // 10
    I2 = 1;
    I1 = 0;
    #20;

    // 11
    I1 = 1;
    I2 = 1;
    #20;

    // test second AND gate
    S = 1;

    // 00
    I2 = 0;
    I1 = 0;
    #20;

    // 01
    I2 = 0;
    I1 = 1;
    #20;

    // 10
    I2 = 1;
    I1 = 0;
    #20;

    // 11
    I1 = 1;
    I2 = 1;
    #20;

    $display("Test complete");

end

endmodule

mux_tb.vcd
$date
	Sat Aug 12 04:19:15 2023
$end
$version
	Icarus Verilog
$end
$timescale
	1ns
$end
$scope module mux_tb $end
$var wire 1 ! R $end
$var reg 1 " I1 $end
$var reg 1 # I2 $end
$var reg 1 $ S $end
$scope module uut $end
$var wire 1 % and_1 $end
$var wire 1 & and_2 $end
$var wire 1 " input_1 $end
$var wire 1 # input_2 $end
$var wire 1 ! result $end
$var wire 1 $ switch $end
$upscope $end
$upscope $end
$enddefinitions $end
$comment Show the parameter values. $end
$dumpall
$end
#0
$dumpvars
0&
0%
0$
0#
0"
0!
$end
#20
1!
1%
1"
#40
0!
0%
0"
1#
#60
1!
1%
1"
#80
0!
0%
0"
0#
1$
#100
1"
#120
1!
1&
0"
1#
#140
1"
